securitygpt/__init__.py
securitygpt/temperature.py
securitygpt/chains/__init__.py
securitygpt/prompts/__init__.py
securitygpt/prompts/prompts_vuln.py
securitygpt/schema/__init__.py
securitygpt/schema/schema_cve.py
securitygpt/vulngpt/__init__.py
securitygpt/vulngpt/cve_gpt.py
securitygpt-0.0.2.4.dist-info/METADATA
securitygpt-0.0.2.4.dist-info/WHEEL
securitygpt-0.0.2.4.dist-info/top_level.txt
securitygpt-0.0.2.4.dist-info/RECORD
