Metadata-Version: 2.1
Name: securitygpt
Version: 0.0.2.4
Summary: SecurityGPT, GPT for security practioners
Author: rkreddyp
Classifier: Programming Language :: Python :: 3
Classifier: License :: OSI Approved :: MIT License
Classifier: Operating System :: OS Independent
Requires-Python: >=3.6
